odoo_client.py
odoo_pyclient-1.0.0.dist-info/licenses/LICENSE
odoo_pyclient-1.0.0.dist-info/METADATA
odoo_pyclient-1.0.0.dist-info/WHEEL
odoo_pyclient-1.0.0.dist-info/top_level.txt
odoo_pyclient-1.0.0.dist-info/RECORD
