Metadata-Version: 2.4
Name: odoo-pyclient
Version: 1.0.0
Summary: Python client for Odoo using the requests library and JSON-RPC
Home-page: https://github.com/mohamed-helmy/OdooPyClient
Author: Mohamed Helmy
Author-email: Mohamed Helmy <helmy419@gmail.com>
License-Expression: MIT
Project-URL: Homepage, https://github.com/mohamed-helmy/OdooPyClient
Project-URL: Bug Reports, https://github.com/mohamed-helmy/OdooPyClient/issues
Project-URL: Source, https://github.com/mohamed-helmy/OdooPyClient
Keywords: odoo,erp,client,api,jsonrpc
Classifier: Development Status :: 4 - Beta
Classifier: Intended Audience :: Developers
Classifier: Topic :: Software Development :: Libraries :: Python Modules
Classifier: Programming Language :: Python :: 3
Classifier: Programming Language :: Python :: 3.7
Classifier: Programming Language :: Python :: 3.8
Classifier: Programming Language :: Python :: 3.9
Classifier: Programming Language :: Python :: 3.10
Classifier: Programming Language :: Python :: 3.11
Classifier: Programming Language :: Python :: 3.12
Requires-Python: >=3.7
License-File: LICENSE
Requires-Dist: requests>=2.25.0
Dynamic: author
Dynamic: home-page
Dynamic: license-file
Dynamic: requires-python
